alu/arithmatic/BitAdder.v
module BitAdder (
    i_clk, // input clock
    i_reset, // input reset
    i_a, // input wire a
    i_b, // input wire b
    i_c, // input wire carry
    o_o, // output wire output 
    o_c // output wire carry 
);
    input wire i_clk;
    input wire i_reset;
    input wire i_a;
    input wire i_b;
    input wire i_c;
    output reg o_o;
    output reg o_c;    

    wire abxor;
    assign abxor = (i_a ^ i_b);

    always @(posedge i_clk) begin
        if (i_reset) begin
            o_o <= 0;
            o_c <= 0;
        end else begin
            o_o <= (abxor ^ i_c);
            o_c <= ((i_c & abxor) | (i_a & i_b));
        end
    end    
endmodule

Test/BitAdder_tb.v
`timescale 1ns / 1ps
`include "../CPU/alu/arithmatic/BitAdder.v"

module BitAdder_tb;

    reg i_clk;
    reg i_reset;
    reg i_a;
    reg i_b;
    reg i_c;
    wire o_o;
    wire o_c;

    // Instantiate the Adder module
    BitAdder uut (
        .i_clk(i_clk),
        .i_reset(i_reset),
        .i_a(i_a),
        .i_b(i_b),
        .i_c(i_c),
        .o_o(o_o),
        .o_c(o_c)
    );

    // Clock generation
    always #5 i_clk = ~i_clk; // Toggle clock every 5 time units

    initial begin

        $dumpfile("BitAdder.vcd");
        $dumpvars(0,BitAdder_tb);

        // Initialize all inputs
        i_clk = 0;
        i_reset = 0;
        i_a = 0;
        i_b = 0;
        i_c = 0;

        // Apply reset
        i_reset = 1;
        #10; // Wait for 10 time units
        i_reset = 0;

        // Test case 1: 0 + 0 + 0 = 0, carry = 0
        i_a = 0;
        i_b = 0;
        i_c = 0;
        #10;

        // Test case 2: 1 + 0 + 0 = 1, carry = 0
        i_a = 1;
        i_b = 0;
        i_c = 0;
        #10;

        // Test case 3: 1 + 1 + 0 = 0, carry = 1
        i_a = 1;
        i_b = 1;
        i_c = 0;
        #10;

        // Test case 4: 1 + 1 + 1 = 1, carry = 1
        i_a = 1;
        i_b = 1;
        i_c = 1;
        #10;

        // End simulation
        $stop;
    end
endmodule

BitAdder.vcd
$date
	Sat Oct  5 13:59:42 2024
$end
$version
	Icarus Verilog
$end
$timescale
	1ps
$end
$scope module BitAdder_tb $end
$var wire 1 ! o_o $end
$var wire 1 " o_c $end
$var reg 1 # i_a $end
$var reg 1 $ i_b $end
$var reg 1 % i_c $end
$var reg 1 & i_clk $end
$var reg 1 ' i_reset $end
$scope module uut $end
$var wire 1 ( abxor $end
$var wire 1 # i_a $end
$var wire 1 $ i_b $end
$var wire 1 % i_c $end
$var wire 1 & i_clk $end
$var wire 1 ' i_reset $end
$var reg 1 " o_c $end
$var reg 1 ! o_o $end
$upscope $end
$upscope $end
$enddefinitions $end
#0
$dumpvars
0(
1'
0&
0%
0$
0#
x"
x!
$end
#5000
0"
0!
1&
#10000
0&
0'
#15000
1&
#20000
1(
0&
1#
#25000
1!
1&
#30000
0(
0&
1$
#35000
1"
0!
1&
#40000
0&
1%
#45000
1!
1&
